installer/__init__.py
installer/custom_installer.py
installer/test_ai_constraints.py
installer/test_installation.py
mkflow_engine/__init__.py
mkflow_engine/cli.py
mkflow_engine/commands/__init__.py
mkflow_engine/commands/command_registry.py
mkflow_engine/commands/docs/commands_index.md
mkflow_engine/commands/docs/end_command.md
mkflow_engine/commands/docs/feedback_command.md
mkflow_engine/commands/docs/help_command.md
mkflow_engine/commands/docs/init_command.md
mkflow_engine/commands/docs/parse_command.md
mkflow_engine/commands/docs/pointer_command.md
mkflow_engine/commands/docs/run_command.md
mkflow_engine/commands/docs/stage_command.md
mkflow_engine/commands/docs/step_command.md
mkflow_engine/core/__init__.py
mkflow_engine/core/workflow_engine.py
mkflow_engine/parser/__init__.py
mkflow_engine/parser/mermaid_parser.py
mkflow_engine/core/workflow_schema.json
mkflow_engine/templates/official_flowchart.mermaid
mkflow_engine-1.0.0.dist-info/METADATA
mkflow_engine-1.0.0.dist-info/WHEEL
mkflow_engine-1.0.0.dist-info/entry_points.txt
mkflow_engine-1.0.0.dist-info/licenses/LICENSE
mkflow_engine-1.0.0.dist-info/RECORD
