Metadata-Version: 2.4
Name: mkflow-engine
Version: 1.0.0
Summary: 基于六大原则的IDE Agent工作流引擎
Project-URL: Documentation, https://github.com/ARSENE2630/moke-work-flow/blob/master/README.md
Project-URL: Source, https://github.com/ARSENE2630/moke-work-flow
Project-URL: Tracker, https://github.com/ARSENE2630/moke-work-flow/issues
Author-email: IDE Agent MKFlow Team <team@mkflow-engine.dev>
License-File: LICENSE
Keywords: agent,automation,ide,mermaid,workflow
Classifier: Development Status :: 4 - Beta
Classifier: Intended Audience :: Developers
Classifier: License :: OSI Approved :: MIT License
Classifier: Programming Language :: Python :: 3
Classifier: Programming Language :: Python :: 3.8
Classifier: Programming Language :: Python :: 3.9
Classifier: Programming Language :: Python :: 3.10
Classifier: Programming Language :: Python :: 3.11
Classifier: Programming Language :: Python :: 3.12
Requires-Python: >=3.8.1
Requires-Dist: click>=8.0.0
Requires-Dist: jsonschema>=4.0.0
Requires-Dist: rich>=13.0.0
Provides-Extra: dev
Requires-Dist: black>=23.0.0; extra == 'dev'
Requires-Dist: flake8>=6.0.0; extra == 'dev'
Requires-Dist: isort>=5.0.0; extra == 'dev'
Requires-Dist: pytest-cov>=4.0.0; extra == 'dev'
Requires-Dist: pytest>=7.0.0; extra == 'dev'
